[
[
    {
        "id": 0,
        "city_name": "神奈川県",
        "code": "140007",
        "area_name": "県全域",
        "city_type": "県",
        "household": 4160450,
        "population": 9199389,
        "pop_male": 4585392,
        "pop_female": 4613997,
        "change_pop": -201,
        "change_nature": -700,
        "change_social": 499,
        "pop_per_house": 2.21,
        "pop_per_area": 3807
    },
    {
        "id": 1,
        "city_name": "市部計",
        "code": "--",
        "area_name": "--",
        "city_type": "--",
        "household": 4040826,
        "population": 8910740,
        "pop_male": 4443395,
        "pop_female": 4467345,
        "change_pop": -17,
        "change_nature": -573,
        "change_social": 556,
        "pop_per_house": 2.21,
        "pop_per_area": 4923
    },
    {
        "id": 2,
        "city_name": "郡部計",
        "code": "--",
        "area_name": "--",
        "city_type": "--",
        "household": 119624,
        "population": 288649,
        "pop_male": 141997,
        "pop_female": 146652,
        "change_pop": -184,
        "change_nature": -127,
        "change_social": -57,
        "pop_per_house": 2.41,
        "pop_per_area": 476
    },
    {
        "id": 3,
        "city_name": "横浜市",
        "code": "141003",
        "area_name": "横浜",
        "city_type": "政令市",
        "household": 1709616,
        "population": 3748473,
        "pop_male": 1862371,
        "pop_female": 1886102,
        "change_pop": 40,
        "change_nature": -238,
        "change_social": 278,
        "pop_per_house": 2.19,
        "pop_per_area": 8567
    },
    {
        "id": 4,
        "city_name": "鶴見区",
        "code": "141011",
        "area_name": "横浜",
        "city_type": "区",
        "household": 139998,
        "population": 292646,
        "pop_male": 151140,
        "pop_female": 141506,
        "change_pop": 110,
        "change_nature": 26,
        "change_social": 84,
        "pop_per_house": 2.09,
        "pop_per_area": 8807
    },
    {
        "id": 5,
        "city_name": "神奈川区",
        "code": "141020",
        "area_name": "横浜",
        "city_type": "区",
        "household": 125807,
        "population": 244625,
        "pop_male": 124106,
        "pop_female": 120519,
        "change_pop": 164,
        "change_nature": 16,
        "change_social": 148,
        "pop_per_house": 1.94,
        "pop_per_area": 10313
    },
    {
        "id": 6,
        "city_name": "西区",
        "code": "141038",
        "area_name": "横浜",
        "city_type": "区",
        "household": 55731,
        "population": 103797,
        "pop_male": 52532,
        "pop_female": 51265,
        "change_pop": 139,
        "change_nature": 20,
        "change_social": 119,
        "pop_per_house": 1.86,
        "pop_per_area": 14765
    },
    {
        "id": 7,
        "city_name": "中区",
        "code": "141046",
        "area_name": "横浜",
        "city_type": "区",
        "household": 81074,
        "population": 149344,
        "pop_male": 78422,
        "pop_female": 70922,
        "change_pop": -16,
        "change_nature": -59,
        "change_social": 43,
        "pop_per_house": 1.84,
        "pop_per_area": 7018
    },
    {
        "id": 8,
        "city_name": "南区",
        "code": "141054",
        "area_name": "横浜",
        "city_type": "区",
        "household": 99897,
        "population": 195868,
        "pop_male": 97609,
        "pop_female": 98259,
        "change_pop": 73,
        "change_nature": -98,
        "change_social": 171,
        "pop_per_house": 1.96,
        "pop_per_area": 15484
    },
    {
        "id": 9,
        "city_name": "港南区",
        "code": "141119",
        "area_name": "横浜",
        "city_type": "区",
        "household": 93943,
        "population": 213992,
        "pop_male": 104869,
        "pop_female": 109123,
        "change_pop": -23,
        "change_nature": -40,
        "change_social": 17,
        "pop_per_house": 2.28,
        "pop_per_area": 10753
    },
    {
        "id": 10,
        "city_name": "保土ケ谷区",
        "code": "141062",
        "area_name": "横浜",
        "city_type": "区",
        "household": 96210,
        "population": 205771,
        "pop_male": 102308,
        "pop_female": 103463,
        "change_pop": 74,
        "change_nature": -28,
        "change_social": 102,
        "pop_per_house": 2.14,
        "pop_per_area": 9383
    },
    {
        "id": 11,
        "city_name": "旭区",
        "code": "141127",
        "area_name": "横浜",
        "city_type": "区",
        "household": 106040,
        "population": 245340,
        "pop_male": 118817,
        "pop_female": 126523,
        "change_pop": -110,
        "change_nature": -61,
        "change_social": -49,
        "pop_per_house": 2.31,
        "pop_per_area": 7496
    },
    {
        "id": 12,
        "city_name": "磯子区",
        "code": "141071",
        "area_name": "横浜",
        "city_type": "区",
        "household": 77007,
        "population": 166564,
        "pop_male": 81971,
        "pop_female": 84593,
        "change_pop": 23,
        "change_nature": -28,
        "change_social": 51,
        "pop_per_house": 2.16,
        "pop_per_area": 8744
    },
    {
        "id": 13,
        "city_name": "金沢区",
        "code": "141089",
        "area_name": "横浜",
        "city_type": "区",
        "household": 88683,
        "population": 198741,
        "pop_male": 97301,
        "pop_female": 101440,
        "change_pop": -174,
        "change_nature": -52,
        "change_social": -122,
        "pop_per_house": 2.24,
        "pop_per_area": 6419
    },
    {
        "id": 14,
        "city_name": "港北区",
        "code": "141097",
        "area_name": "横浜",
        "city_type": "区",
        "household": 170381,
        "population": 352875,
        "pop_male": 178253,
        "pop_female": 174622,
        "change_pop": -104,
        "change_nature": 115,
        "change_social": -219,
        "pop_per_house": 2.07,
        "pop_per_area": 11238
    },
    {
        "id": 15,
        "city_name": "緑区",
        "code": "141135",
        "area_name": "横浜",
        "city_type": "区",
        "household": 77781,
        "population": 182127,
        "pop_male": 89584,
        "pop_female": 92543,
        "change_pop": 122,
        "change_nature": 12,
        "change_social": 110,
        "pop_per_house": 2.34,
        "pop_per_area": 7139
    },
    {
        "id": 16,
        "city_name": "青葉区",
        "code": "141178",
        "area_name": "横浜",
        "city_type": "区",
        "household": 129173,
        "population": 310088,
        "pop_male": 150487,
        "pop_female": 159601,
        "change_pop": 50,
        "change_nature": -1,
        "change_social": 51,
        "pop_per_house": 2.4,
        "pop_per_area": 8804
    },
    {
        "id": 17,
        "city_name": "都筑区",
        "code": "141186",
        "area_name": "横浜",
        "city_type": "区",
        "household": 83537,
        "population": 212269,
        "pop_male": 105645,
        "pop_female": 106624,
        "change_pop": 14,
        "change_nature": 49,
        "change_social": -35,
        "pop_per_house": 2.54,
        "pop_per_area": 7616
    },
    {
        "id": 18,
        "city_name": "戸塚区",
        "code": "141101",
        "area_name": "横浜",
        "city_type": "区",
        "household": 119259,
        "population": 280327,
        "pop_male": 137079,
        "pop_female": 143248,
        "change_pop": -129,
        "change_nature": -4,
        "change_social": -125,
        "pop_per_house": 2.35,
        "pop_per_area": 7833
    },
    {
        "id": 19,
        "city_name": "栄区",
        "code": "141151",
        "area_name": "横浜",
        "city_type": "区",
        "household": 51545,
        "population": 119870,
        "pop_male": 58354,
        "pop_female": 61516,
        "change_pop": -115,
        "change_nature": -16,
        "change_social": -99,
        "pop_per_house": 2.33,
        "pop_per_area": 6472
    },
    {
        "id": 20,
        "city_name": "泉区",
        "code": "141160",
        "area_name": "横浜",
        "city_type": "区",
        "household": 62140,
        "population": 151968,
        "pop_male": 74254,
        "pop_female": 77714,
        "change_pop": 33,
        "change_nature": -42,
        "change_social": 75,
        "pop_per_house": 2.45,
        "pop_per_area": 6445
    },
    {
        "id": 21,
        "city_name": "瀬谷区",
        "code": "141143",
        "area_name": "横浜",
        "city_type": "区",
        "household": 51410,
        "population": 122261,
        "pop_male": 59640,
        "pop_female": 62621,
        "change_pop": -91,
        "change_nature": -47,
        "change_social": -44,
        "pop_per_house": 2.38,
        "pop_per_area": 7121
    },
    {
        "id": 22,
        "city_name": "川崎市",
        "code": "141305",
        "area_name": "川崎",
        "city_type": "政令市",
        "household": 739465,
        "population": 1529251,
        "pop_male": 773665,
        "pop_female": 755586,
        "change_pop": 810,
        "change_nature": 371,
        "change_social": 439,
        "pop_per_house": 2.07,
        "pop_per_area": 10693
    },
    {
        "id": 23,
        "city_name": "川崎区",
        "code": "141313",
        "area_name": "川崎",
        "city_type": "区",
        "household": 120185,
        "population": 233055,
        "pop_male": 125268,
        "pop_female": 107787,
        "change_pop": -3,
        "change_nature": -20,
        "change_social": 17,
        "pop_per_house": 1.94,
        "pop_per_area": 5896
    },
    {
        "id": 24,
        "city_name": "幸区",
        "code": "141321",
        "area_name": "川崎",
        "city_type": "区",
        "household": 81145,
        "population": 169736,
        "pop_male": 85664,
        "pop_female": 84072,
        "change_pop": 304,
        "change_nature": 54,
        "change_social": 250,
        "pop_per_house": 2.09,
        "pop_per_area": 16957
    },
    {
        "id": 25,
        "city_name": "中原区",
        "code": "141330",
        "area_name": "川崎",
        "city_type": "区",
        "household": 132801,
        "population": 261448,
        "pop_male": 133167,
        "pop_female": 128281,
        "change_pop": 129,
        "change_nature": 173,
        "change_social": -44,
        "pop_per_house": 1.97,
        "pop_per_area": 17737
    },
    {
        "id": 26,
        "city_name": "高津区",
        "code": "141348",
        "area_name": "川崎",
        "city_type": "区",
        "household": 113036,
        "population": 233106,
        "pop_male": 116981,
        "pop_female": 116125,
        "change_pop": 141,
        "change_nature": 43,
        "change_social": 98,
        "pop_per_house": 2.06,
        "pop_per_area": 14249
    },
    {
        "id": 27,
        "city_name": "宮前区",
        "code": "141364",
        "area_name": "川崎",
        "city_type": "区",
        "household": 100644,
        "population": 232382,
        "pop_male": 113455,
        "pop_female": 118927,
        "change_pop": 68,
        "change_nature": 46,
        "change_social": 22,
        "pop_per_house": 2.31,
        "pop_per_area": 12487
    },
    {
        "id": 28,
        "city_name": "多摩区",
        "code": "141356",
        "area_name": "川崎",
        "city_type": "区",
        "household": 113151,
        "population": 219734,
        "pop_male": 112118,
        "pop_female": 107616,
        "change_pop": -29,
        "change_nature": 32,
        "change_social": -61,
        "pop_per_house": 1.94,
        "pop_per_area": 10719
    },
    {
        "id": 29,
        "city_name": "麻生区",
        "code": "141372",
        "area_name": "川崎",
        "city_type": "区",
        "household": 78503,
        "population": 179790,
        "pop_male": 87012,
        "pop_female": 92778,
        "change_pop": 200,
        "change_nature": 43,
        "change_social": 157,
        "pop_per_house": 2.29,
        "pop_per_area": 7733
    },
    {
        "id": 30,
        "city_name": "相模原市",
        "code": "141500",
        "area_name": "県央",
        "city_type": "政令市",
        "household": 326525,
        "population": 722630,
        "pop_male": 361375,
        "pop_female": 361255,
        "change_pop": -108,
        "change_nature": -99,
        "change_social": -9,
        "pop_per_house": 2.21,
        "pop_per_area": 2197
    },
    {
        "id": 31,
        "city_name": "緑区",
        "code": "141135",
        "area_name": "県央",
        "city_type": "区",
        "household": 73992,
        "population": 170938,
        "pop_male": 86059,
        "pop_female": 84879,
        "change_pop": -178,
        "change_nature": -25,
        "change_social": -153,
        "pop_per_house": 2.31,
        "pop_per_area": 673
    },
    {
        "id": 32,
        "city_name": "中央区",
        "code": "141526",
        "area_name": "県央",
        "city_type": "区",
        "household": 122518,
        "population": 271992,
        "pop_male": 136659,
        "pop_female": 135333,
        "change_pop": -124,
        "change_nature": -47,
        "change_social": -77,
        "pop_per_house": 2.22,
        "pop_per_area": 7377
    },
    {
        "id": 33,
        "city_name": "南区",
        "code": "141054",
        "area_name": "県央",
        "city_type": "区",
        "household": 130015,
        "population": 279700,
        "pop_male": 138657,
        "pop_female": 141043,
        "change_pop": 194,
        "change_nature": -27,
        "change_social": 221,
        "pop_per_house": 2.15,
        "pop_per_area": 7339
    },
    {
        "id": 34,
        "city_name": "横須賀市",
        "code": "142018",
        "area_name": "横須賀三浦",
        "city_type": "中核市",
        "household": 167254,
        "population": 394698,
        "pop_male": 196912,
        "pop_female": 197786,
        "change_pop": -1008,
        "change_nature": -190,
        "change_social": -818,
        "pop_per_house": 2.36,
        "pop_per_area": 3915
    },
    {
        "id": 35,
        "city_name": "平塚市",
        "code": "142034",
        "area_name": "湘南",
        "city_type": "特例市",
        "household": 112100,
        "population": 257864,
        "pop_male": 129074,
        "pop_female": 128790,
        "change_pop": 35,
        "change_nature": -39,
        "change_social": 74,
        "pop_per_house": 2.3,
        "pop_per_area": 3802
    },
    {
        "id": 36,
        "city_name": "鎌倉市",
        "code": "142042",
        "area_name": "横須賀三浦",
        "city_type": "一般市",
        "household": 74806,
        "population": 172238,
        "pop_male": 80978,
        "pop_female": 91260,
        "change_pop": -73,
        "change_nature": -93,
        "change_social": 20,
        "pop_per_house": 2.3,
        "pop_per_area": 4342
    },
    {
        "id": 37,
        "city_name": "藤沢市",
        "code": "142051",
        "area_name": "湘南",
        "city_type": "一般市",
        "household": 190679,
        "population": 434313,
        "pop_male": 214652,
        "pop_female": 219661,
        "change_pop": 203,
        "change_nature": -12,
        "change_social": 215,
        "pop_per_house": 2.28,
        "pop_per_area": 6244
    },
    {
        "id": 38,
        "city_name": "小田原市",
        "code": "142069",
        "area_name": "県西",
        "city_type": "特例市",
        "household": 81741,
        "population": 190318,
        "pop_male": 92489,
        "pop_female": 97829,
        "change_pop": -73,
        "change_nature": -61,
        "change_social": -12,
        "pop_per_house": 2.33,
        "pop_per_area": 1672
    },
    {
        "id": 39,
        "city_name": "茅ヶ崎市",
        "code": "142077",
        "area_name": "湘南",
        "city_type": "特例市",
        "household": 102783,
        "population": 241981,
        "pop_male": 117762,
        "pop_female": 124219,
        "change_pop": -10,
        "change_nature": -21,
        "change_social": 11,
        "pop_per_house": 2.35,
        "pop_per_area": 6778
    },
    {
        "id": 40,
        "city_name": "逗子市",
        "code": "142085",
        "area_name": "横須賀三浦",
        "city_type": "一般市",
        "household": 24630,
        "population": 56958,
        "pop_male": 26603,
        "pop_female": 30355,
        "change_pop": 9,
        "change_nature": -31,
        "change_social": 40,
        "pop_per_house": 2.31,
        "pop_per_area": 3296
    },
    {
        "id": 41,
        "city_name": "三浦市",
        "code": "142107",
        "area_name": "横須賀三浦",
        "city_type": "一般市",
        "household": 17530,
        "population": 42594,
        "pop_male": 20468,
        "pop_female": 22126,
        "change_pop": -13,
        "change_nature": -31,
        "change_social": 18,
        "pop_per_house": 2.43,
        "pop_per_area": 1329
    },
    {
        "id": 42,
        "city_name": "秦野市",
        "code": "142115",
        "area_name": "湘南",
        "city_type": "一般市",
        "household": 72030,
        "population": 165100,
        "pop_male": 84563,
        "pop_female": 80537,
        "change_pop": 13,
        "change_nature": -20,
        "change_social": 33,
        "pop_per_house": 2.29,
        "pop_per_area": 1591
    },
    {
        "id": 43,
        "city_name": "厚木市",
        "code": "142123",
        "area_name": "県央",
        "city_type": "特例市",
        "household": 100332,
        "population": 224851,
        "pop_male": 116361,
        "pop_female": 108490,
        "change_pop": -7,
        "change_nature": -48,
        "change_social": 41,
        "pop_per_house": 2.24,
        "pop_per_area": 2396
    },
    {
        "id": 44,
        "city_name": "大和市",
        "code": "142131",
        "area_name": "県央",
        "city_type": "特例市",
        "household": 108210,
        "population": 237230,
        "pop_male": 118577,
        "pop_female": 118653,
        "change_pop": 153,
        "change_nature": 17,
        "change_social": 136,
        "pop_per_house": 2.19,
        "pop_per_area": 8757
    },
    {
        "id": 45,
        "city_name": "伊勢原市",
        "code": "142140",
        "area_name": "湘南",
        "city_type": "一般市",
        "household": 45493,
        "population": 102220,
        "pop_male": 51823,
        "pop_female": 50397,
        "change_pop": -4,
        "change_nature": -19,
        "change_social": 15,
        "pop_per_house": 2.25,
        "pop_per_area": 1840
    },
    {
        "id": 46,
        "city_name": "海老名市",
        "code": "142158",
        "area_name": "県央",
        "city_type": "一般市",
        "household": 56945,
        "population": 133165,
        "pop_male": 67020,
        "pop_female": 66145,
        "change_pop": -16,
        "change_nature": 5,
        "change_social": -21,
        "pop_per_house": 2.34,
        "pop_per_area": 5008
    },
    {
        "id": 47,
        "city_name": "座間市",
        "code": "142166",
        "area_name": "県央",
        "city_type": "一般市",
        "household": 59189,
        "population": 130568,
        "pop_male": 65063,
        "pop_female": 65505,
        "change_pop": 150,
        "change_nature": -2,
        "change_social": 152,
        "pop_per_house": 2.21,
        "pop_per_area": 7431
    },
    {
        "id": 48,
        "city_name": "南足柄市",
        "code": "142174",
        "area_name": "県西",
        "city_type": "一般市",
        "household": 16582,
        "population": 41907,
        "pop_male": 20631,
        "pop_female": 21276,
        "change_pop": -57,
        "change_nature": -24,
        "change_social": -33,
        "pop_per_house": 2.53,
        "pop_per_area": 543
    },
    {
        "id": 49,
        "city_name": "綾瀬市",
        "code": "142182",
        "area_name": "県央",
        "city_type": "一般市",
        "household": 34916,
        "population": 84381,
        "pop_male": 43008,
        "pop_female": 41373,
        "change_pop": -61,
        "change_nature": -38,
        "change_social": -23,
        "pop_per_house": 2.42,
        "pop_per_area": 3811
    },
    {
        "id": 50,
        "city_name": "葉山町",
        "code": "143014",
        "area_name": "横須賀三浦",
        "city_type": "町村",
        "household": 12721,
        "population": 31708,
        "pop_male": 14977,
        "pop_female": 16731,
        "change_pop": 10,
        "change_nature": -6,
        "change_social": 16,
        "pop_per_house": 2.49,
        "pop_per_area": 1861
    },
    {
        "id": 51,
        "city_name": "寒川町",
        "code": "143219",
        "area_name": "湘南",
        "city_type": "町村",
        "household": 19731,
        "population": 48357,
        "pop_male": 24503,
        "pop_female": 23854,
        "change_pop": -13,
        "change_nature": -5,
        "change_social": -8,
        "pop_per_house": 2.45,
        "pop_per_area": 3625
    },
    {
        "id": 52,
        "city_name": "中郡",
        "code": "--",
        "area_name": "--",
        "city_type": "--",
        "household": 24108,
        "population": 59123,
        "pop_male": 28702,
        "pop_female": 30421,
        "change_pop": -71,
        "change_nature": -39,
        "change_social": -32,
        "pop_per_house": 2.45,
        "pop_per_area": 2252
    },
    {
        "id": 53,
        "city_name": "大磯町",
        "code": "143413",
        "area_name": "湘南",
        "city_type": "町村",
        "household": 12671,
        "population": 31343,
        "pop_male": 15305,
        "pop_female": 16038,
        "change_pop": -27,
        "change_nature": -21,
        "change_social": -6,
        "pop_per_house": 2.47,
        "pop_per_area": 1824
    },
    {
        "id": 54,
        "city_name": "二宮町",
        "code": "143421",
        "area_name": "湘南",
        "city_type": "町村",
        "household": 11437,
        "population": 27780,
        "pop_male": 13397,
        "pop_female": 14383,
        "change_pop": -44,
        "change_nature": -18,
        "change_social": -26,
        "pop_per_house": 2.43,
        "pop_per_area": 3059
    },
    {
        "id": 55,
        "city_name": "足柄上郡",
        "code": "--",
        "area_name": "--",
        "city_type": "--",
        "household": 25082,
        "population": 65001,
        "pop_male": 32062,
        "pop_female": 32939,
        "change_pop": 2,
        "change_nature": -12,
        "change_social": 14,
        "pop_per_house": 2.59,
        "pop_per_area": 214
    },
    {
        "id": 56,
        "city_name": "中井町",
        "code": "143618",
        "area_name": "県西",
        "city_type": "町村",
        "household": 3444,
        "population": 9389,
        "pop_male": 4718,
        "pop_female": 4671,
        "change_pop": 3,
        "change_nature": -5,
        "change_social": 8,
        "pop_per_house": 2.73,
        "pop_per_area": 470
    },
    {
        "id": 57,
        "city_name": "大井町",
        "code": "143626",
        "area_name": "県西",
        "city_type": "町村",
        "household": 6483,
        "population": 17069,
        "pop_male": 8474,
        "pop_female": 8595,
        "change_pop": 39,
        "change_nature": 3,
        "change_social": 36,
        "pop_per_house": 2.63,
        "pop_per_area": 1187
    },
    {
        "id": 58,
        "city_name": "松田町",
        "code": "143634",
        "area_name": "県西",
        "city_type": "町村",
        "household": 4535,
        "population": 10870,
        "pop_male": 5372,
        "pop_female": 5498,
        "change_pop": -54,
        "change_nature": -6,
        "change_social": -48,
        "pop_per_house": 2.4,
        "pop_per_area": 288
    },
    {
        "id": 59,
        "city_name": "山北町",
        "code": "143642",
        "area_name": "県西",
        "city_type": "町村",
        "household": 3855,
        "population": 9707,
        "pop_male": 4767,
        "pop_female": 4940,
        "change_pop": -17,
        "change_nature": -10,
        "change_social": -7,
        "pop_per_house": 2.52,
        "pop_per_area": 43
    },
    {
        "id": 60,
        "city_name": "開成町",
        "code": "143669",
        "area_name": "県西",
        "city_type": "町村",
        "household": 6765,
        "population": 17966,
        "pop_male": 8731,
        "pop_female": 9235,
        "change_pop": 31,
        "change_nature": 6,
        "change_social": 25,
        "pop_per_house": 2.66,
        "pop_per_area": 2743
    },
    {
        "id": 61,
        "city_name": "足柄下郡",
        "code": "--",
        "area_name": "--",
        "city_type": "--",
        "household": 20126,
        "population": 41933,
        "pop_male": 19627,
        "pop_female": 22306,
        "change_pop": -64,
        "change_nature": -54,
        "change_social": -10,
        "pop_per_house": 2.08,
        "pop_per_area": 298
    },
    {
        "id": 62,
        "city_name": "箱根町",
        "code": "143821",
        "area_name": "県西",
        "city_type": "町村",
        "household": 6249,
        "population": 11236,
        "pop_male": 5364,
        "pop_female": 5872,
        "change_pop": -29,
        "change_nature": -14,
        "change_social": -15,
        "pop_per_house": 1.8,
        "pop_per_area": 121
    },
    {
        "id": 63,
        "city_name": "真鶴町",
        "code": "143839",
        "area_name": "県西",
        "city_type": "町村",
        "household": 3048,
        "population": 6850,
        "pop_male": 3203,
        "pop_female": 3647,
        "change_pop": -9,
        "change_nature": -13,
        "change_social": 4,
        "pop_per_house": 2.25,
        "pop_per_area": 972
    },
    {
        "id": 64,
        "city_name": "湯河原町",
        "code": "143847",
        "area_name": "県西",
        "city_type": "町村",
        "household": 10829,
        "population": 23847,
        "pop_male": 11060,
        "pop_female": 12787,
        "change_pop": -26,
        "change_nature": -27,
        "change_social": 1,
        "pop_per_house": 2.2,
        "pop_per_area": 582
    },
    {
        "id": 65,
        "city_name": "愛甲郡",
        "code": "--",
        "area_name": "--",
        "city_type": "--",
        "household": 17856,
        "population": 42527,
        "pop_male": 22126,
        "pop_female": 20401,
        "change_pop": -48,
        "change_nature": -11,
        "change_social": -37,
        "pop_per_house": 2.38,
        "pop_per_area": 403
    },
    {
        "id": 66,
        "city_name": "愛川町",
        "code": "144011",
        "area_name": "県央",
        "city_type": "町村",
        "household": 16702,
        "population": 39432,
        "pop_male": 20551,
        "pop_female": 18881,
        "change_pop": -34,
        "change_nature": -8,
        "change_social": -26,
        "pop_per_house": 2.36,
        "pop_per_area": 1150
    },
    {
        "id": 67,
        "city_name": "清川村",
        "code": "144029",
        "area_name": "県央",
        "city_type": "町村",
        "household": 1154,
        "population": 3095,
        "pop_male": 1575,
        "pop_female": 1520,
        "change_pop": -14,
        "change_nature": -3,
        "change_social": -11,
        "pop_per_house": 2.68,
        "pop_per_area": 43
    }
]
]